pyBNS-0.1.2.dist-info/LICENSE.txt
pyBNS-0.1.2.dist-info/METADATA
pyBNS-0.1.2.dist-info/RECORD
pyBNS-0.1.2.dist-info/WHEEL
pyBNS-0.1.2.dist-info/top_level.txt
pybns/__init__.py
pybns/pybns.py
